jaq.cpython-310-x86_64-linux-gnu.so
jaq-0.0.1.dist-info/METADATA
jaq-0.0.1.dist-info/WHEEL
jaq-0.0.1.dist-info/RECORD
jaq-0.0.1.dist-info/LICENSE
jaq-0.0.1.dist-info/top_level.txt
