Metadata-Version: 2.1
Name: jaq
Version: 0.0.1
Summary: A Json-Array Query tool
Home-page: https://github.com/cubao/jaq
Author: tzx
Author-email: dvorak4tzx@gmail.com
License: UNKNOWN
Platform: UNKNOWN
Provides-Extra: test
Requires-Dist: pytest (>=6.0) ; extra == 'test'
